falcon/__init__.py
falcon/_typing.py
falcon/app.py
falcon/app_helpers.py
falcon/asgi_spec.py
falcon/constants.py
falcon/errors.py
falcon/forwarded.py
falcon/hooks.py
falcon/http_error.py
falcon/http_status.py
falcon/inspect.py
falcon/middleware.py
falcon/py.typed
falcon/redirects.py
falcon/request.py
falcon/request_helpers.py
falcon/responders.py
falcon/response.py
falcon/response_helpers.py
falcon/status_codes.py
falcon/stream.py
falcon/typing.py
falcon/uri.py
falcon/version.py
falcon/asgi/__init__.py
falcon/asgi/_asgi_helpers.py
falcon/asgi/_request_helpers.py
falcon/asgi/app.py
falcon/asgi/multipart.py
falcon/asgi/reader.py
falcon/asgi/request.py
falcon/asgi/response.py
falcon/asgi/stream.py
falcon/asgi/structures.py
falcon/asgi/ws.py
falcon/bench/__init__.py
falcon/bench/bench.py
falcon/bench/create.py
falcon/bench/dj/__init__.py
falcon/bench/dj/manage.py
falcon/bench/dj/dj/__init__.py
falcon/bench/dj/dj/settings.py
falcon/bench/dj/dj/urls.py
falcon/bench/dj/dj/wsgi.py
falcon/bench/dj/hello/__init__.py
falcon/bench/dj/hello/admin.py
falcon/bench/dj/hello/apps.py
falcon/bench/dj/hello/models.py
falcon/bench/dj/hello/tests.py
falcon/bench/dj/hello/views.py
falcon/bench/dj/hello/migrations/__init__.py
falcon/bench/nuts/__init__.py
falcon/bench/nuts/config.py
falcon/bench/nuts/setup.py
falcon/bench/nuts/nuts/__init__.py
falcon/bench/nuts/nuts/app.py
falcon/bench/nuts/nuts/controllers/__init__.py
falcon/bench/nuts/nuts/controllers/root.py
falcon/bench/nuts/nuts/model/__init__.py
falcon/bench/nuts/nuts/tests/__init__.py
falcon/bench/nuts/nuts/tests/config.py
falcon/bench/nuts/nuts/tests/test_functional.py
falcon/bench/nuts/nuts/tests/test_units.py
falcon/bench/queues/__init__.py
falcon/bench/queues/api.py
falcon/bench/queues/claims.py
falcon/bench/queues/messages.py
falcon/bench/queues/queues.py
falcon/bench/queues/stats.py
falcon/cmd/__init__.py
falcon/cmd/bench.py
falcon/cmd/inspect_app.py
falcon/cyutil/__init__.py
falcon/cyutil/misc.pyx
falcon/cyutil/reader.pyx
falcon-4.2.0.dist-info/licenses/LICENSE
falcon-4.2.0.dist-info/METADATA
falcon-4.2.0.dist-info/WHEEL
falcon-4.2.0.dist-info/entry_points.txt
falcon-4.2.0.dist-info/top_level.txt
falcon-4.2.0.dist-info/RECORD
