Metadata-Version: 2.4
Name: falcon
Version: 4.2.0
Summary: The ultra-reliable, fast ASGI+WSGI framework for building data plane APIs at scale.
Author-email: Kurt Griffiths <mail@kgriffs.com>
License: Apache 2.0
Project-URL: Homepage, https://falconframework.org
Project-URL: Documentation, https://falcon.readthedocs.io/en/stable/
Project-URL: Release Notes, https://falcon.readthedocs.io/en/stable/changes/
Project-URL: Source, https://github.com/falconry/falcon
Project-URL: Issue Tracker, https://github.com/falconry/falcon/issues
Project-URL: Funding, https://opencollective.com/falcon
Project-URL: Chat, https://gitter.im/falconry/user
Keywords: asgi,wsgi,web,api,framework,rest,http,cloud
Classifier: Development Status :: 5 - Production/Stable
Classifier: Environment :: Web Environment
Classifier: Natural Language :: English
Classifier: Intended Audience :: Developers
Classifier: Intended Audience :: System Administrators
Classifier: License :: OSI Approved :: Apache Software License
Classifier: Operating System :: MacOS :: MacOS X
Classifier: Operating System :: Microsoft :: Windows
Classifier: Operating System :: POSIX
Classifier: Topic :: Internet :: WWW/HTTP :: WSGI
Classifier: Topic :: Software Development :: Libraries :: Application Frameworks
Classifier: Programming Language :: Python
Classifier: Programming Language :: Python :: Implementation :: CPython
Classifier: Programming Language :: Python :: Implementation :: PyPy
Classifier: Programming Language :: Python :: 3
Classifier: Programming Language :: Python :: 3.9
Classifier: Programming Language :: Python :: 3.10
Classifier: Programming Language :: Python :: 3.11
Classifier: Programming Language :: Python :: 3.12
Classifier: Programming Language :: Python :: 3.13
Classifier: Programming Language :: Python :: 3.14
Classifier: Programming Language :: Python :: Free Threading
Classifier: Programming Language :: Python :: Free Threading :: 2 - Beta
Classifier: Programming Language :: Cython
Classifier: Typing :: Typed
Requires-Python: >=3.9
License-File: LICENSE
Provides-Extra: test
Requires-Dist: pytest; extra == "test"
Dynamic: license-file
